fastfft/__init__.py
fastfft/fft.cpython-39-x86_64-linux-gnu.so
fastfft-0.2.3.dist-info/METADATA
fastfft-0.2.3.dist-info/RECORD
fastfft-0.2.3.dist-info/LICENSE.txt
fastfft-0.2.3.dist-info/top_level.txt
fastfft-0.2.3.dist-info/WHEEL
